{
  "id": "8c66f7aa-e8cc-40ab-9922-33c70f978aa2",
  "prevId": "00000000-0000-0000-0000-000000000000",
  "version": "7",
  "dialect": "postgresql",
  "tables": {
    "public.users": {
      "name": "users",
      "schema": "",
      "columns": {
        "id": {
          "name": "id",
          "type": "integer",
          "primaryKey": true,
          "notNull": true,
          "identity": {
            "type": "always",
            "name": "users_id_seq",
            "schema": "public",
            "increment": "1",
            "startWith": "1",
            "minValue": "1",
            "maxValue": "2147483647",
            "cache": "1",
            "cycle": false
          }
        },
        "clerk_id": {
          "name": "clerk_id",
          "type": "text",
          "primaryKey": false,
          "notNull": true
        },
        "email": {
          "name": "email",
          "type": "text",
          "primaryKey": false,
          "notNull": false
        },
        "first_name": {
          "name": "first_name",
          "type": "text",
          "primaryKey": false,
          "notNull": false
        },
        "last_name": {
          "name": "last_name",
          "type": "text",
          "primaryKey": false,
          "notNull": false
        },
        "telephone": {
          "name": "telephone",
          "type": "text",
          "primaryKey": false,
          "notNull": false
        },
        "wallet": {
          "name": "wallet",
          "type": "text",
          "primaryKey": false,
          "notNull": false
        },
        "username": {
          "name": "username",
          "type": "text",
          "primaryKey": false,
          "notNull": false
        },
        "image_url": {
          "name": "image_url",
          "type": "text",
          "primaryKey": false,
          "notNull": false
        },
        "last_sign_in_at": {
          "name": "last_sign_in_at",
          "type": "text",
          "primaryKey": false,
          "notNull": false
        },
        "birthday": {
          "name": "birthday",
          "type": "text",
          "primaryKey": false,
          "notNull": false
        },
        "created_at": {
          "name": "created_at",
          "type": "timestamp",
          "primaryKey": false,
          "notNull": true,
          "default": "now()"
        },
        "updated_at": {
          "name": "updated_at",
          "type": "timestamp",
          "primaryKey": false,
          "notNull": true,
          "default": "now()"
        }
      },
      "indexes": {},
      "foreignKeys": {},
      "compositePrimaryKeys": {},
      "uniqueConstraints": {
        "users_clerk_id_unique": {
          "name": "users_clerk_id_unique",
          "nullsNotDistinct": false,
          "columns": [
            "clerk_id"
          ]
        },
        "users_email_unique": {
          "name": "users_email_unique",
          "nullsNotDistinct": false,
          "columns": [
            "email"
          ]
        }
      },
      "policies": {},
      "checkConstraints": {},
      "isRLSEnabled": false
    },
    "public.users_to_wallets": {
      "name": "users_to_wallets",
      "schema": "",
      "columns": {
        "user_id": {
          "name": "user_id",
          "type": "integer",
          "primaryKey": false,
          "notNull": true
        },
        "wallet_id": {
          "name": "wallet_id",
          "type": "integer",
          "primaryKey": false,
          "notNull": true
        }
      },
      "indexes": {},
      "foreignKeys": {
        "users_to_wallets_user_id_users_id_fk": {
          "name": "users_to_wallets_user_id_users_id_fk",
          "tableFrom": "users_to_wallets",
          "tableTo": "users",
          "columnsFrom": [
            "user_id"
          ],
          "columnsTo": [
            "id"
          ],
          "onDelete": "no action",
          "onUpdate": "no action"
        },
        "users_to_wallets_wallet_id_wallets_id_fk": {
          "name": "users_to_wallets_wallet_id_wallets_id_fk",
          "tableFrom": "users_to_wallets",
          "tableTo": "wallets",
          "columnsFrom": [
            "wallet_id"
          ],
          "columnsTo": [
            "id"
          ],
          "onDelete": "no action",
          "onUpdate": "no action"
        }
      },
      "compositePrimaryKeys": {
        "users_to_wallets_user_id_wallet_id_pk": {
          "name": "users_to_wallets_user_id_wallet_id_pk",
          "columns": [
            "user_id",
            "wallet_id"
          ]
        }
      },
      "uniqueConstraints": {},
      "policies": {},
      "checkConstraints": {},
      "isRLSEnabled": false
    },
    "public.wallets": {
      "name": "wallets",
      "schema": "",
      "columns": {
        "id": {
          "name": "id",
          "type": "integer",
          "primaryKey": true,
          "notNull": true,
          "identity": {
            "type": "always",
            "name": "wallets_id_seq",
            "schema": "public",
            "increment": "1",
            "startWith": "1",
            "minValue": "1",
            "maxValue": "2147483647",
            "cache": "1",
            "cycle": false
          }
        },
        "name": {
          "name": "name",
          "type": "text",
          "primaryKey": false,
          "notNull": true
        },
        "network": {
          "name": "network",
          "type": "text",
          "primaryKey": false,
          "notNull": true
        },
        "address": {
          "name": "address",
          "type": "text",
          "primaryKey": false,
          "notNull": true
        }
      },
      "indexes": {},
      "foreignKeys": {},
      "compositePrimaryKeys": {},
      "uniqueConstraints": {},
      "policies": {},
      "checkConstraints": {},
      "isRLSEnabled": false
    }
  },
  "enums": {},
  "schemas": {},
  "sequences": {},
  "roles": {},
  "policies": {},
  "views": {},
  "_meta": {
    "columns": {},
    "schemas": {},
    "tables": {}
  }
}